auto_typing_final/__init__.py
auto_typing_final/finder.py
auto_typing_final/lsp.py
auto_typing_final/main.py
auto_typing_final/transform.py
auto_typing_final-1.0.3.dist-info/METADATA
auto_typing_final-1.0.3.dist-info/WHEEL
auto_typing_final-1.0.3.dist-info/entry_points.txt
auto_typing_final-1.0.3.dist-info/licenses/LICENSE
auto_typing_final-1.0.3.dist-info/RECORD
