Metadata-Version: 2.4
Name: auto-typing-final
Version: 1.0.3
Summary: Automagically set typing.Final inside your functions
Project-URL: Repository, https://github.com/community-of-python/auto-typing-final
Author-email: Lev Vereshchagin <mail@vrslev.com>
License: MIT
License-File: LICENSE
Keywords: automation,flake8,mypy,typing
Classifier: Development Status :: 4 - Beta
Classifier: Natural Language :: English
Classifier: Programming Language :: Python :: Implementation :: CPython
Classifier: Typing :: Typed
Requires-Python: >=3.10
Requires-Dist: ast-grep-py==0.40.3
Requires-Dist: pygls==1.3.1
